{"name":"ZED_Switch_BLE_TRSP","type":"ARM","mode":"RT581_MPB","toolchain":"GCC","dependenceList":[{"groupName":"custom","depList":[{"name":"default","sourceDirList":[],"libList":[],"incList":[".\\..\\Zigbee_App\\Include",".\\..\\BLE_App_Profile\\Include",".\\..\\config",".\\..\\Include",".\\..\\..\\..\\..\\..\\Library\\CMSIS\\Include",".\\..\\..\\..\\..\\..\\Library\\RT58x\\include",".\\..\\..\\..\\..\\..\\Library\\RT58x\\Crypto\\include",".\\..\\..\\..\\..\\..\\Library\\RT58x\\Peripheral\\Include",".\\..\\..\\..\\..\\..\\Library\\RT58x\\PHY\\include",".\\..\\..\\..\\..\\..\\Library\\RT58x\\Device\\Include",".\\..\\..\\..\\..\\..\\Middleware\\Third_Party\\FreeRTOS\\Source\\portable\\GCC\\ARM_CM3",".\\..\\..\\..\\..\\..\\Middleware\\Third_Party\\FreeRTOS\\Source\\Include",".\\..\\..\\..\\..\\..\\Middleware\\Portable\\Utility\\include",".\\..\\..\\..\\..\\..\\Middleware\\Portable\\System\\Include",".\\..\\..\\..\\..\\..\\Middleware\\Portable\\bsp\\Include",".\\..\\..\\..\\..\\..\\Middleware\\MemoryMgmt\\Include",".\\..\\..\\..\\..\\..\\Middleware\\RFB\\include",".\\..\\..\\..\\..\\..\\Middleware\\RUCI\\include",".\\..\\..\\..\\..\\..\\Middleware\\RF_FW_Control_Task\\Include",".\\..\\..\\..\\..\\..\\Middleware\\Zigbee\\Include",".\\..\\..\\..\\..\\..\\Middleware\\Zigbee\\Include\\osif",".\\..\\..\\..\\..\\..\\Middleware\\BLE\\Portable\\Include",".\\..\\..\\..\\..\\..\\Middleware\\BLE\\BLE_Host\\Include",".\\..\\..\\..\\..\\..\\Middleware\\BLE\\BLE_Service\\BLE_Service_Common\\Include",".\\..\\..\\..\\..\\..\\Middleware\\BLE\\BLE_Service\\GAPS\\Include",".\\..\\..\\..\\..\\..\\Middleware\\BLE\\BLE_Service\\DIS\\Include",".\\..\\..\\..\\..\\..\\Middleware\\BLE\\BLE_Service\\GATTS\\Include",".\\..\\..\\..\\..\\..\\Middleware\\BLE\\BLE_Service\\TRSPS\\Include",".\\..\\..\\..\\..\\..\\Middleware\\FOTA\\Include",".\\.eide\\deps",".\\..\\..\\..\\..\\..\\Middleware\\Zigbee\\Include\\ZCL",".\\..\\..\\..\\..\\..\\Library\\RT58x\\PHY\\rt569mp\\include"],"defineList":["CHIP_VERSION=RT58X_MPB","BOARD=A048"]}]}],"compileConfig":{"cpuType":"Cortex-M3","floatingPointHardware":"none","useCustomScatterFile":true,"scatterFilePath":".\\..\\..\\..\\..\\..\\Library\\RT58x\\Device\\GCC\\app_gcc_cm3_mcu.ld","storageLayout":{"RAM":[{"tag":"IRAM","id":1,"mem":{"startAddr":"0x20000000","size":"0x5000"},"isChecked":true,"noInit":false}],"ROM":[{"tag":"IROM","id":1,"mem":{"startAddr":"0x08000000","size":"0x10000"},"isChecked":true,"isStartup":true}]},"options":"null"},"uploader":"JLink","srcDirs":[".\\.eide\\deps"],"virtualFolder":{"name":"<virtual_root>","files":[],"folders":[{"name":"::CMSIS","files":[],"folders":[]},{"name":"Application","files":[{"path":".\\..\\main.c"},{"path":".\\..\\multi_app.c"}],"folders":[]},{"name":"Application_BLE","files":[{"path":".\\..\\BLE_App_Profile\\ble_profile_app.c"},{"path":".\\..\\BLE_App_Profile\\ble_profile_def.c"},{"path":".\\..\\BLE_App_Profile\\ble_app.c"}],"folders":[]},{"name":"Application_Zigbee","files":[{"path":".\\..\\Zigbee_App\\zigbee_app.c"},{"path":".\\..\\Zigbee_App\\zigbee_data.c"},{"path":".\\..\\Zigbee_App\\zigbee_evt_handler.c"},{"path":".\\..\\Zigbee_App\\zigbee_zcl_msg_handler.c"}],"folders":[]},{"name":"BLE_Host","files":[{"path":".\\..\\..\\..\\..\\..\\Middleware\\BLE\\BLE_Host\\ble_cmd_advertising.c"},{"path":".\\..\\..\\..\\..\\..\\Middleware\\BLE\\BLE_Host\\ble_cmd_att_gatt.c"},{"path":".\\..\\..\\..\\..\\..\\Middleware\\BLE\\BLE_Host\\ble_cmd_common.c"},{"path":".\\..\\..\\..\\..\\..\\Middleware\\BLE\\BLE_Host\\ble_cmd_gap.c"},{"path":".\\..\\..\\..\\..\\..\\Middleware\\BLE\\BLE_Host\\ble_cmd_privacy.c"},{"path":".\\..\\..\\..\\..\\..\\Middleware\\BLE\\BLE_Host\\ble_cmd_scan.c"},{"path":".\\..\\..\\..\\..\\..\\Middleware\\BLE\\BLE_Host\\ble_cmd_security_manager.c"},{"path":".\\..\\..\\..\\..\\..\\Middleware\\BLE\\BLE_Host\\ble_host_ref.c"},{"path":".\\..\\..\\..\\..\\..\\Middleware\\Prebuild\\lib_ble_host.a"}],"folders":[]},{"name":"BLE_Service","files":[{"path":".\\..\\..\\..\\..\\..\\Middleware\\BLE\\BLE_Service\\BLE_Service_Common\\ble_service_common.c"},{"path":".\\..\\..\\..\\..\\..\\Middleware\\BLE\\BLE_Service\\DIS\\ble_service_dis.c"},{"path":".\\..\\..\\..\\..\\..\\Middleware\\BLE\\BLE_Service\\GAPS\\ble_service_gaps.c"},{"path":".\\..\\..\\..\\..\\..\\Middleware\\BLE\\BLE_Service\\GATTS\\ble_service_gatts.c"},{"path":".\\..\\..\\..\\..\\..\\Middleware\\BLE\\BLE_Service\\TRSPS\\ble_service_trsps.c"}],"folders":[]},{"name":"BSP","files":[{"path":".\\..\\..\\..\\..\\..\\Middleware\\Portable\\bsp\\bsp_button.c"},{"path":".\\..\\..\\..\\..\\..\\Middleware\\Portable\\bsp\\bsp_console.c"},{"path":".\\..\\..\\..\\..\\..\\Middleware\\Portable\\bsp\\bsp_led.c"},{"path":".\\..\\..\\..\\..\\..\\Middleware\\Portable\\bsp\\bsp_uart.c"},{"path":".\\..\\..\\..\\..\\..\\Middleware\\Portable\\bsp\\bsp.c"}],"folders":[]},{"name":"FreeRTOS","files":[{"path":".\\..\\..\\..\\..\\..\\Middleware\\Third_Party\\FreeRTOS\\Source\\list.c"},{"path":".\\..\\..\\..\\..\\..\\Middleware\\Third_Party\\FreeRTOS\\Source\\portable\\GCC\\ARM_CM3\\port.c"},{"path":".\\..\\..\\..\\..\\..\\Middleware\\Third_Party\\FreeRTOS\\Source\\portable\\MemMang\\heap_4.c"},{"path":".\\..\\..\\..\\..\\..\\Middleware\\Third_Party\\FreeRTOS\\Source\\queue.c"},{"path":".\\..\\..\\..\\..\\..\\Middleware\\Third_Party\\FreeRTOS\\Source\\tasks.c"},{"path":".\\..\\..\\..\\..\\..\\Middleware\\Third_Party\\FreeRTOS\\Source\\timers.c"},{"path":".\\..\\config\\FreeRTOSConfig.h"}],"folders":[]},{"name":"Library","files":[{"path":".\\..\\..\\..\\..\\..\\Library\\RT58x\\Crypto\\aes.c"},{"path":".\\..\\..\\..\\..\\..\\Library\\RT58x\\Crypto\\crypto_util.c"},{"path":".\\..\\..\\..\\..\\..\\Library\\RT58x\\Crypto\\crypto.c"},{"path":".\\..\\..\\..\\..\\..\\Library\\RT58x\\Peripheral\\dma.c"},{"path":".\\..\\..\\..\\..\\..\\Library\\RT58x\\Peripheral\\flashctl.c"},{"path":".\\..\\..\\..\\..\\..\\Library\\RT58x\\Peripheral\\gpio.c"},{"path":".\\..\\..\\..\\..\\..\\Library\\RT58x\\Peripheral\\lpm.c"},{"path":".\\..\\..\\..\\..\\..\\Library\\RT58x\\Peripheral\\mp_sector.c"},{"path":".\\..\\..\\..\\..\\..\\Library\\RT58x\\Peripheral\\sadc.c"},{"path":".\\..\\..\\..\\..\\..\\Library\\RT58x\\Peripheral\\sysctrl.c"},{"path":".\\..\\..\\..\\..\\..\\Library\\RT58x\\Peripheral\\sysfun.c"},{"path":".\\..\\..\\..\\..\\..\\Library\\RT58x\\Peripheral\\timer.c"},{"path":".\\..\\..\\..\\..\\..\\Library\\RT58x\\Peripheral\\uart_drv.c"},{"path":".\\..\\..\\..\\..\\..\\Library\\RT58x\\Peripheral\\uart_retarget.c"}],"folders":[]},{"name":"MemMgmt","files":[{"path":".\\..\\..\\..\\..\\..\\Middleware\\MemoryMgmt\\mem_mgmt.c"}],"folders":[]},{"name":"Multi_Protocol","files":[{"path":".\\..\\..\\..\\..\\..\\Middleware\\Prebuild\\lib_dual_task.a"}],"folders":[]},{"name":"Phy","files":[{"path":".\\..\\..\\..\\..\\..\\Library\\RT58x\\PHY\\rf_common_init.c"},{"path":".\\..\\..\\..\\..\\..\\Library\\RT58x\\PHY\\rf_tx_comp.c"},{"path":".\\..\\..\\..\\..\\..\\Library\\RT58x\\PHY\\rt569mp\\rt569mp_fw.c"},{"path":".\\..\\..\\..\\..\\..\\Library\\RT58x\\PHY\\rt569mp\\rt569mp_init.c"}],"folders":[]},{"name":"Startup","files":[{"path":".\\..\\..\\..\\..\\..\\Library\\RT58x\\Device\\GCC\\gcc_startup_cm3_mcu.S"},{"path":".\\..\\..\\..\\..\\..\\Library\\RT58x\\Device\\system_cm3_mcu.c"}],"folders":[]},{"name":"System","files":[{"path":".\\..\\..\\..\\..\\..\\Middleware\\Portable\\System\\sys_arch.c"},{"path":".\\..\\..\\..\\..\\..\\Middleware\\Portable\\System\\sys_memory.c"},{"path":".\\..\\..\\..\\..\\..\\Middleware\\Portable\\System\\sys_taskdbg.c"},{"path":".\\..\\..\\..\\..\\..\\Middleware\\Portable\\System\\sys_timer.c"}],"folders":[]},{"name":"Utility","files":[{"path":".\\..\\..\\..\\..\\..\\Middleware\\Portable\\Utility\\fsm.c"},{"path":".\\..\\..\\..\\..\\..\\Middleware\\Portable\\Utility\\shell.c"},{"path":".\\..\\..\\..\\..\\..\\Middleware\\Portable\\Utility\\util_bda.c"},{"path":".\\..\\..\\..\\..\\..\\Middleware\\Portable\\Utility\\util_bstream.c"},{"path":".\\..\\..\\..\\..\\..\\Middleware\\Portable\\Utility\\util_fcs.c"},{"path":".\\..\\..\\..\\..\\..\\Middleware\\Portable\\Utility\\util_list.c"},{"path":".\\..\\..\\..\\..\\..\\Middleware\\Portable\\Utility\\util_log.c"},{"path":".\\..\\..\\..\\..\\..\\Middleware\\Portable\\Utility\\util_printf.c"},{"path":".\\..\\..\\..\\..\\..\\Middleware\\Portable\\Utility\\util_queue.c"},{"path":".\\..\\..\\..\\..\\..\\Middleware\\Portable\\Utility\\util_string.c"},{"path":".\\..\\..\\..\\..\\..\\Middleware\\Portable\\Utility\\util.c"}],"folders":[]},{"name":"ZigBee","files":[{"path":".\\..\\..\\..\\..\\..\\Middleware\\Prebuild\\lib_zigbee_stack_ed.a"},{"path":".\\..\\..\\..\\..\\..\\Middleware\\Zigbee\\zigbee_lib_api.c"}],"folders":[]}]},"excludeList":["<virtual_root>/Phy/rf_common_init.c"],"outDir":".\\build","deviceName":null,"packDir":null,"uploadConfig":{"bin":"","baseAddr":"0x08000000","cpuInfo":{"vendor":"Rafael","cpuName":"ARMCM3"},"proType":1,"speed":8000,"otherCmds":""},"uploadConfigMap":{},"miscInfo":{"uid":"93747b8b25312465ab17093fc1ae8bd6"},"targets":{"RT581_MPB":{"excludeList":[],"toolchain":"GCC","compileConfig":{"cpuType":"Cortex-M3","floatingPointHardware":"none","useCustomScatterFile":true,"scatterFilePath":".\\..\\..\\..\\..\\..\\Library\\RT58x\\Device\\GCC\\app_gcc_cm3_mcu.ld","storageLayout":{"RAM":[{"tag":"IRAM","id":1,"mem":{"startAddr":"0x20000000","size":"0x5000"},"isChecked":true,"noInit":false}],"ROM":[{"tag":"IROM","id":1,"mem":{"startAddr":"0x08000000","size":"0x10000"},"isChecked":true,"isStartup":true}]},"options":"null"},"uploader":"JLink","uploadConfig":{"bin":null,"baseAddr":"0x08000000","cpuInfo":{"vendor":"Rafael","cpuName":"ARMCM3"},"proType":1,"speed":8000,"otherCmds":""},"uploadConfigMap":{},"custom_dep":{"name":"default","sourceDirList":[],"libList":[],"incList":[".\\..\\Zigbee_App\\Include",".\\..\\BLE_App_Profile\\Include",".\\..\\config",".\\..\\Include",".\\..\\..\\..\\..\\..\\Library\\CMSIS\\Include",".\\..\\..\\..\\..\\..\\Library\\RT58x\\include",".\\..\\..\\..\\..\\..\\Library\\RT58x\\Peripheral\\Include",".\\..\\..\\..\\..\\..\\Library\\RT58x\\PHY\\include",".\\..\\..\\..\\..\\..\\Library\\RT58x\\PHY\\rf_fw",".\\..\\..\\..\\..\\..\\Library\\RT58x\\Device\\Include",".\\..\\..\\..\\..\\..\\Middleware\\Third_Party\\FreeRTOS\\Source\\portable\\GCC\\ARM_CM3",".\\..\\..\\..\\..\\..\\Middleware\\Third_Party\\FreeRTOS\\Source\\Include",".\\..\\..\\..\\..\\..\\Middleware\\Third_Party\\ZBOSS\\Include",".\\..\\..\\..\\..\\..\\Middleware\\Portable\\Utility\\include",".\\..\\..\\..\\..\\..\\Middleware\\Portable\\System\\Include",".\\..\\..\\..\\..\\..\\Middleware\\Portable\\bsp\\Include",".\\..\\..\\..\\..\\..\\Middleware\\MemoryMgmt\\Include",".\\..\\..\\..\\..\\..\\Middleware\\RFB\\include",".\\..\\..\\..\\..\\..\\Middleware\\RUCI\\include",".\\..\\..\\..\\..\\..\\Middleware\\RF_FW_Control_Task\\Include",".\\..\\..\\..\\..\\..\\Middleware\\Zigbee\\Include",".\\..\\..\\..\\..\\..\\Middleware\\Zigbee\\Include\\osif",".\\..\\..\\..\\..\\..\\Middleware\\BLE\\Portable\\Include",".\\..\\..\\..\\..\\..\\Middleware\\BLE\\BLE_Host\\Include",".\\..\\..\\..\\..\\..\\Middleware\\BLE\\BLE_Service\\BLE_Service_Common\\Include",".\\..\\..\\..\\..\\..\\Middleware\\BLE\\BLE_Service\\GAPS\\Include",".\\..\\..\\..\\..\\..\\Middleware\\BLE\\BLE_Service\\DIS\\Include",".\\..\\..\\..\\..\\..\\Middleware\\BLE\\BLE_Service\\GATTS\\Include",".\\..\\..\\..\\..\\..\\Middleware\\BLE\\BLE_Service\\TRSPS\\Include",".\\..\\..\\..\\..\\..\\Middleware\\FOTA\\Include",".\\.eide\\deps"],"defineList":["CHIP_VERSION=RT58X_MPB","BOARD=A048"]}}},"version":"2.6"}